MANIFEST.in
README.md
setup.py
../pygame-2.6.1_opencv-4.11.0_for_QPython-3.8.11_py3.12/pygame/__init__.py
../pygame-2.6.1_opencv-4.11.0_for_QPython-3.8.11_py3.12/pygame/__init__.pyi
../pygame-2.6.1_opencv-4.11.0_for_QPython-3.8.11_py3.12/pygame/_camera.cpython-312.so
../pygame-2.6.1_opencv-4.11.0_for_QPython-3.8.11_py3.12/pygame/_camera_opencv.py
../pygame-2.6.1_opencv-4.11.0_for_QPython-3.8.11_py3.12/pygame/_camera_vidcapture.py
../pygame-2.6.1_opencv-4.11.0_for_QPython-3.8.11_py3.12/pygame/_common.pyi
../pygame-2.6.1_opencv-4.11.0_for_QPython-3.8.11_py3.12/pygame/_freetype.cpython-312.so
../pygame-2.6.1_opencv-4.11.0_for_QPython-3.8.11_py3.12/pygame/_sprite.cpython-312.so
../pygame-2.6.1_opencv-4.11.0_for_QPython-3.8.11_py3.12/pygame/base.cpython-312.so
../pygame-2.6.1_opencv-4.11.0_for_QPython-3.8.11_py3.12/pygame/base.pyi
../pygame-2.6.1_opencv-4.11.0_for_QPython-3.8.11_py3.12/pygame/bufferproxy.cpython-312.so
../pygame-2.6.1_opencv-4.11.0_for_QPython-3.8.11_py3.12/pygame/bufferproxy.pyi
../pygame-2.6.1_opencv-4.11.0_for_QPython-3.8.11_py3.12/pygame/camera.py
../pygame-2.6.1_opencv-4.11.0_for_QPython-3.8.11_py3.12/pygame/camera.pyi
../pygame-2.6.1_opencv-4.11.0_for_QPython-3.8.11_py3.12/pygame/color.cpython-312.so
../pygame-2.6.1_opencv-4.11.0_for_QPython-3.8.11_py3.12/pygame/color.pyi
../pygame-2.6.1_opencv-4.11.0_for_QPython-3.8.11_py3.12/pygame/colordict.py
../pygame-2.6.1_opencv-4.11.0_for_QPython-3.8.11_py3.12/pygame/constants.cpython-312.so
../pygame-2.6.1_opencv-4.11.0_for_QPython-3.8.11_py3.12/pygame/constants.pyi
../pygame-2.6.1_opencv-4.11.0_for_QPython-3.8.11_py3.12/pygame/cursors.py
../pygame-2.6.1_opencv-4.11.0_for_QPython-3.8.11_py3.12/pygame/cursors.pyi
../pygame-2.6.1_opencv-4.11.0_for_QPython-3.8.11_py3.12/pygame/display.cpython-312.so
../pygame-2.6.1_opencv-4.11.0_for_QPython-3.8.11_py3.12/pygame/display.pyi
../pygame-2.6.1_opencv-4.11.0_for_QPython-3.8.11_py3.12/pygame/draw.cpython-312.so
pygame_qpython.egg-info/PKG-INFO
pygame_qpython.egg-info/SOURCES.txt
pygame_qpython.egg-info/dependency_links.txt
pygame_qpython.egg-info/requires.txt
pygame_qpython.egg-info/top_level.txt